CHANGES.rst
CONTRIBUTORS.rst
MANIFEST.in
README.rst
bootstrap.py
buildout.cfg
setup.py
travis.cfg
buildout.d/base.cfg
buildout.d/checkouts.cfg
buildout.d/development.cfg
buildout.d/jenkins.cfg
buildout.d/sources.cfg
buildout.d/versions.cfg
docs/LICENSE.GPL
docs/LICENSE.rst
src/imio/__init__.py
src/imio.urban.core.egg-info/PKG-INFO
src/imio.urban.core.egg-info/SOURCES.txt
src/imio.urban.core.egg-info/dependency_links.txt
src/imio.urban.core.egg-info/entry_points.txt
src/imio.urban.core.egg-info/namespace_packages.txt
src/imio.urban.core.egg-info/not-zip-safe
src/imio.urban.core.egg-info/requires.txt
src/imio.urban.core.egg-info/top_level.txt
src/imio/urban/__init__.py
src/imio/urban/core/__init__.py
src/imio/urban/core/configure.zcml
src/imio/urban/core/import_steps.zcml
src/imio/urban/core/interfaces.py
src/imio/urban/core/overrides.zcml
src/imio/urban/core/profiles.zcml
src/imio/urban/core/setuphandlers.py
src/imio/urban/core/testing.py
src/imio/urban/core/testing.zcml
src/imio/urban/core/upgrades.py
src/imio/urban/core/upgrades.zcml
src/imio/urban/core/actionspanel/__init__.py
src/imio/urban/core/actionspanel/configure.zcml
src/imio/urban/core/actionspanel/views.py
src/imio/urban/core/actionspanel/tests/__init__.py
src/imio/urban/core/actionspanel/tests/test_actions_display.py
src/imio/urban/core/browser/__init__.py
src/imio/urban/core/browser/configure.zcml
src/imio/urban/core/browser/widgets.py
src/imio/urban/core/browser/static/.gitkeep
src/imio/urban/core/browser/static/EventConfig.png
src/imio/urban/core/browser/static/EventConfig.png.metadata
src/imio/urban/core/contents/__init__.py
src/imio/urban/core/contents/configure.zcml
src/imio/urban/core/contents/utils.py
src/imio/urban/core/contents/eventconfig/__init__.py
src/imio/urban/core/contents/eventconfig/configure.zcml
src/imio/urban/core/contents/eventconfig/content.py
src/imio/urban/core/contents/eventconfig/vocabularies.py
src/imio/urban/core/contents/eventconfig/tests/__init__.py
src/imio/urban/core/contents/eventconfig/tests/test_eventconfig.py
src/imio/urban/core/contents/eventconfig/tests/test_vocabularies.py
src/imio/urban/core/contents/followupeventconfig/__init__.py
src/imio/urban/core/contents/followupeventconfig/configure.zcml
src/imio/urban/core/contents/followupeventconfig/content.py
