Metadata-Version: 2.1
Name: imio.urban.core
Version: 0.3
Summary: Core of application managing urban and environment licences for townships.
Home-page: http://pypi.python.org/pypi/imio.urban.core
Author: Simon Declourt
Author-email: simon.delcourt@imio.be
License: GPL
Keywords: urban imio
Classifier: Environment :: Web Environment
Classifier: Framework :: Plone
Classifier: Framework :: Plone :: 4.3
Classifier: Programming Language :: Python
Classifier: Programming Language :: Python :: 2.7
Classifier: License :: OSI Approved :: GNU General Public License v2 (GPLv2)
Provides-Extra: test
